{"ASMAP1C":{"runway":"LTFM35L","points":["TH17M","TH17R","YH010","YH070","YH071","YH052","YH053","YH054","YH055","YH056","ASMAP"]},"ASMAP1F":{"runway":"LTFM36R","points":["TH18M","TH18L","YH030","YH050","YH051","YH052","YH053","YH054","YH055","YH056","ASMAP"]},"ASMAP1G":{"runway":"LTFM36R","points":["TH18M","TH18L","YH030","YH050","YH059","YH052","YH053","YH054","YH055","YH056","ASMAP"]},"DUMMY":{"runway":"XXXX00","points":["DUMM1","DUMM2"]},"SGB1C":{"runway":"LTFM35L","points":["TH17M","TH17R","YH010","YH070","YH071","YH072","YH073","YH074","YH075","YH076","YH077","YH081","SGB1"]},"SGB1D":{"runway":"LTFM35L","points":["TH17M","TH17R","YH010","YH070","YH079","YH072","YH073","YH074","YH075","YH076","YH077","YH081","SGB1"]},"SGB1F":{"runway":"LTFM36R","points":["TH18M","TH18L","YH030","YH050","YH051","YH052","YH073","YH074","YH075","YH076","YH077","YH081","SGB1"]},"SGB1G":{"runway":"LTFM36R","points":["TH18M","TH18L","YH030","YH050","YH059","YH052","YH073","YH074","YH075","YH076","YH077","YH081","SGB1"]},"YENID1C":{"runway":"LTFM35L","points":["TH17M","TH17R","YH010","YH020","YH031","YH042","YH043","YENID"]},"YENID1F":{"runway":"LTFM36R","points":["TH18M","TH18L","YH030","YH032","YH031","YH042","YH043","YENID"]},"YH0611C":{"runway":"LTFM35L","points":["TH17M","TH17R","YH010","YH070","YH071","YH052","YH053","YH060","YH061"]},"YH0611F":{"runway":"LTFM36R","points":["TH18M","TH18L","YH030","YH050","YH051","YH052","YH053","YH060","YH061"]},"YH0611G":{"runway":"LTFM36R","points":["TH18M","TH18L","YH030","YH050","YH059","YH052","YH053","YH060","YH061"]},"YHGOL1C":{"runway":"LTFM35L","points":["TH17M","TH17R","YH010","YH070","YH071","YH072","YH073","YH074","YH075","YH076","YH077","YH078","YHGOL"]},"YHGOL1D":{"runway":"LTFM35L","points":["TH17M","TH17R","YH010","YH070","YH079","YH072","YH073","YH074","YH075","YH076","YH077","YH078","YHGOL"]},"YHGOL1F":{"runway":"LTFM36R","points":["TH18M","TH18L","YH030","YH050","YH051","YH052","YH073","YH074","YH075","YH076","YH078","YHGOL"]},"YHGOL1G":{"runway":"LTFM36R","points":["TH18M","TH18L","YH030","YH050","YH059","YH052","YH073","YH074","YH075","YH076","YH078","YHGOL"]},"YHIBL1C":{"runway":"LTFM35L","points":["TH17M","TH17R","YH010","YH020","YH021","YH022","IBLAL"]},"YHIBL1F":{"runway":"LTFM36R","points":["TH18M","TH18L","YH030","YH040","YH082","IBLAL"]},"YHMAK1C":{"runway":"LTFM35L","points":["TH17M","TH17R","YH010","YH020","YH031","MAKOL"]},"YHMAK1F":{"runway":"LTFM36R","points":["TH18M","TH18L","YH030","YH032","YH031","MAKOL"]},"YHTUD1C":{"runway":"LTFM35L","points":["TH17M","TH17R","YH010","YH015","YH016","YH017","TUDBU"]},"YHTUD1F":{"runway":"LTFM36R","points":["TH18M","TH18L","YH030","YH040","YH631","YH021","TUDBU"]},"YHVAD1C":{"runway":"LTFM35L","points":["TH17M","TH17R","YH010","YH011","YH012","VADEN"]},"YHVAD1F":{"runway":"LTFM36R","points":["TH18M","TH18L","YH030","YH040","YH631","YH021","YH012","VADEN"]}}