[{"callsign":"AFR2331","type":"A318","dep":"18:25:00","adep":"EDDT","ades":"LFPG","route":"ABAMI_KENUM","rfl":340,"tas":450,"efl":340,"points":{"sid":null,"star":null,"points":["ABAMI",null,"KENUM"]}},{"callsign":"AFR2335","type":"A318","dep":"18:27:00","adep":"EDDT","ades":"LFPG","route":"ABAMI_KENUM","rfl":340,"tas":450,"efl":340,"points":{"sid":null,"star":null,"points":["ABAMI",null,"KENUM"]}},{"callsign":"AFR6741","type":"B744","dep":"18:25:30","adep":"ZSPD","ades":"LFPG","route":"DEKEL_KENUM","rfl":360,"tas":489,"efl":360,"points":{"sid":null,"star":null,"points":["DEKEL","DLE",null,"OSN",null,"KENUM"]}},{"callsign":"BRT761","type":"E145","dep":"18:28:10","adep":"EDDF","ades":"EGBB","route":"EDDF_LOGAN_007","rfl":360,"tas":442,"efl":240,"points":{"sid":null,"star":null,"points":["EDDF","BIBOS",null,"THN",null,"REFSO",null,"LOGAN"]}},{"callsign":"BRT76B","type":"E145","dep":"18:29:10","adep":"EDDF","ades":"EGBB","route":"EDDF_LOGAN_007","rfl":360,"tas":442,"efl":240,"points":{"sid":null,"star":null,"points":["EDDF","BIBOS",null,"THN",null,"REFSO",null,"LOGAN"]}},{"callsign":"BRT76C","type":"E145","dep":"18:28:40","adep":"EDDF","ades":"EGBB","route":"EDDF_LOGAN_007","rfl":360,"tas":442,"efl":240,"points":{"sid":null,"star":null,"points":["EDDF","BIBOS",null,"THN",null,"REFSO",null,"LOGAN"]}},{"callsign":"BTI656","type":"B735","dep":"18:36:10","adep":"EGKK","ades":"EYVI","route":"BRAIN_JUIST_001","rfl":350,"tas":438,"efl":350,"points":{"sid":null,"star":null,"points":["BRAIN",null,"TULIP",null,"JUIST"]}},{"callsign":"CTN450","type":"A319","dep":"18:42:50","adep":"LDZA","ades":"EHAM","route":"GORKO_EHAM_005","rfl":380,"tas":450,"efl":380,"points":{"sid":null,"star":null,"points":["GORKO",null,"BIGGE",null,"SONSA","EHAM"]}},{"callsign":"DLH071","type":"A319","dep":"18:34:10","adep":"EDDH","ades":"EDDL","route":"EDDH_BOT_007","rfl":280,"tas":450,"efl":240,"points":{"sid":null,"star":null,"points":["EDDH","BASUM",null,"OSN",null,"BOT"]}},{"callsign":"DLH071B","type":"A319","dep":"18:35:10","adep":"EDDH","ades":"EDDL","route":"EDDH_BOT_007","rfl":280,"tas":450,"efl":240,"points":{"sid":null,"star":null,"points":["EDDH","BASUM",null,"OSN",null,"BOT"]}},{"callsign":"DLH109","type":"RJ85","dep":"18:41:20","adep":"EDDK","ades":"EDDH","route":"EDDK_WSR_007","rfl":290,"tas":411,"efl":240,"points":{"sid":null,"star":null,"points":["EDDK","DOM",null,"BASUM","WSR"]}},{"callsign":"DLH109B","type":"RJ85","dep":"18:42:20","adep":"EDDK","ades":"EDDH","route":"EDDK_WSR_007","rfl":290,"tas":411,"efl":240,"points":{"sid":null,"star":null,"points":["EDDK","DOM",null,"BASUM","WSR"]}},{"callsign":"DLH109C","type":"RJ85","dep":"18:43:20","adep":"EDDK","ades":"EDDH","route":"EDDK_WSR_007","rfl":290,"tas":411,"efl":240,"points":{"sid":null,"star":null,"points":["EDDK","DOM",null,"BASUM","WSR"]}},{"callsign":"DLH3207","type":"B733","dep":"18:38:50","adep":"EDDL","ades":"EDDH","route":"EDDL_WSR_005","rfl":290,"tas":427,"efl":240,"points":{"sid":null,"star":null,"points":["EDDL","MEVEL",null,"BASUM","WSR"]}},{"callsign":"DLH4AF","type":"CRJ1","dep":"18:39:20","adep":"EBBR","ades":"EDDT","route":"EBBR_DLE_007","rfl":330,"tas":442,"efl":240,"points":{"sid":null,"star":null,"points":["EBBR","KENUM",null,"ABAMI",null,"DLE"]}},{"callsign":"DLH5A","type":"A320","dep":"18:31:00","adep":"EHAM","ades":"EDDF","route":"EHAM_ROLIS_006","rfl":290,"tas":450,"efl":290,"points":{"sid":null,"star":null,"points":["EHAM","PAM",null,"ARNEM",null,"TEBRO",null,"ROLIS"]}},{"callsign":"DLH5AB","type":"A320","dep":"18:33:00","adep":"EHAM","ades":"EDDF","route":"EHAM_ROLIS_006","rfl":290,"tas":450,"efl":290,"points":{"sid":null,"star":null,"points":["EHAM","PAM",null,"ARNEM",null,"TEBRO",null,"ROLIS"]}},{"callsign":"DLH5AC","type":"A320","dep":"18:32:10","adep":"EHAM","ades":"EDDF","route":"EHAM_ROLIS_006","rfl":290,"tas":450,"efl":290,"points":{"sid":null,"star":null,"points":["EHAM","PAM",null,"ARNEM",null,"TEBRO",null,"ROLIS"]}},{"callsign":"LOT232","type":"B735","dep":"18:30:10","adep":"EBBR","ades":"EPWA","route":"EBBR_DLE_007","rfl":370,"tas":438,"efl":240,"points":{"sid":null,"star":null,"points":["EBBR","KENUM",null,"ABAMI",null,"DLE"]}},{"callsign":"MAS6166","type":"B742","dep":"18:24:30","adep":"OMDB","ades":"EHAM","route":"DEKEL_EHAM_007","rfl":340,"tas":477,"efl":340,"points":{"sid":null,"star":null,"points":["DEKEL","DLE",null,"AMSAN",null,"SONSA","EHAM"]}},{"callsign":"OLT886","type":"SB20","dep":"18:29:40","adep":"LFBO","ades":"EDDW","route":"DIK_BASUM_003","rfl":280,"tas":369,"efl":280,"points":{"sid":null,"star":null,"points":["DIK","ARCKY",null,"ABAMI",null,"OSN","BASUM"]}},{"callsign":"RAE503","type":"E145","dep":"18:44:20","adep":"LFPG","ades":"EDDV","route":"DIK_EDDV_005","rfl":350,"tas":442,"efl":350,"points":{"sid":null,"star":null,"points":["DIK","ARCKY",null,"ABAMI",null,"OSN","EDDV"]}},{"callsign":"RYR684","type":"B738","dep":"18:26:10","adep":"EGSS","ades":"ESOW","route":"BRAIN_JUIST_009","rfl":370,"tas":453,"efl":370,"points":{"sid":null,"star":null,"points":["BRAIN",null,"ARTOV",null,"SOMVA",null,"ANDIK",null,"JUIST"]}},{"callsign":"RYR684B","type":"B738","dep":"18:25:10","adep":"EGSS","ades":"ESOW","route":"BRAIN_JUIST_009","rfl":370,"tas":453,"efl":370,"points":{"sid":null,"star":null,"points":["BRAIN",null,"ARTOV",null,"SOMVA",null,"ANDIK",null,"JUIST"]}},{"callsign":"SAS623","type":"B736","dep":"18:40:10","adep":"ENGM","ades":"EDDL","route":"EKERN_BOT_006","rfl":380,"tas":447,"efl":380,"points":{"sid":null,"star":null,"points":["EKERN",null,"LBE",null,"OSN",null,"BOT"]}},{"callsign":"TRA5468","type":"B737","dep":"18:41:50","adep":"LIPX","ades":"EHAM","route":"GORKO_EHAM_005","rfl":400,"tas":447,"efl":400,"points":{"sid":null,"star":null,"points":["GORKO",null,"BIGGE",null,"SONSA","EHAM"]}}]